Metadata-Version: 2.1
Name: llamirhosseinll
Version: 1.0.1
Summary: this is a test
Home-page: https://github.com/llamirhosseinll?tab=repositories
Author: amirhossein rezaei
Author-email: awmirhossein5@gmail.com
License: Apache 2.0
Platform: UNKNOWN
License-File: LICENSE.txt
